README.md
setup.cfg
setup.py
spotlob/__init__.py
spotlob/analyze_circle.py
spotlob/analyze_line.py
spotlob/batch.py
spotlob/calculation.py
spotlob/calibration.py
spotlob/defaults.py
spotlob/logger.py
spotlob/output.py
spotlob/parameters.py
spotlob/pipeline.py
spotlob/preview.py
spotlob/process.py
spotlob/process_opencv.py
spotlob/process_steps.py
spotlob/register.py
spotlob/review.py
spotlob/spim.py
spotlob/version.py
spotlob/widget.py
spotlob.egg-info/PKG-INFO
spotlob.egg-info/SOURCES.txt
spotlob.egg-info/dependency_links.txt
spotlob.egg-info/requires.txt
spotlob.egg-info/top_level.txt