Metadata-Version: 2.1
Name: spotlob
Version: 0.9.1a0
Summary: feature extraction and analysis pipeline for image data
Home-page: https://gitlab.cc-asp.fraunhofer.de/fmeyer/spotlob
Author: Fabian Meyer
Author-email: fabian.meyer@ise.fraunhofer.de
License: BSD 3-clause
Platform: UNKNOWN
Classifier: Development Status :: 3 - Alpha
Classifier: Intended Audience :: Science/Research
Classifier: License :: OSI Approved :: BSD License
Classifier: Natural Language :: English
Classifier: Programming Language :: Python :: 3 :: Only
Classifier: Topic :: Scientific/Engineering :: Image Recognition
